zmp_openapi_helper/__init__.py
zmp_openapi_helper/models/mixed_spec.py
zmp_openapi_helper/models/operation.py
zmp_openapi_helper/openapi/fastapi_models.py
zmp_openapi_helper/openapi/openapi_helper.py
zmp_openapi_helper/openapi/zmpapi_models.py
zmp_openapi_helper/wrapper/api_wrapper.py
zmp_openapi_helper-0.2.1.dist-info/LICENSE
zmp_openapi_helper-0.2.1.dist-info/METADATA
zmp_openapi_helper-0.2.1.dist-info/WHEEL
zmp_openapi_helper-0.2.1.dist-info/RECORD
