Metadata-Version: 2.3
Name: zmp-openapi-helper
Version: 0.2.1
Summary: This is a openapi helper library for the ZMP AI Platform
Author: Kilsoo Kang
Author-email: kilsoo75@gmail.com
Requires-Python: >=3.11, <4.0
Classifier: Programming Language :: Python :: 3
Classifier: Programming Language :: Python :: 3.11
Classifier: Programming Language :: Python :: 3.12
Classifier: Programming Language :: Python :: 3.13
Requires-Dist: colorlog (>=6.9.0,<7.0.0)
Requires-Dist: httpx (>=0.28.1,<0.29.0)
Requires-Dist: pydantic (>=2.10.6)
Requires-Dist: python-dotenv (>=1.0.1,<2.0.0)
Project-URL: Bug Tracker, https://github.com/cloudz-mp/zmp-openapi-helper/issues
Project-URL: Documentation, https://github.com/cloudz-mp/zmp-openapi-helper
Project-URL: Homepage, https://github.com/cloudz-mp
Project-URL: Repository, https://github.com/cloudz-mp/zmp-openapi-helper
